ppic/__init__.py
ppic/compat.py
ppic/resource.py
ppic/tests/__init__.py
ppic/tests/test_collect_request_list.py
ppic/tests/test_get_info.py
ppic/tests/test_guess_stable_version.py
ppic/tests/test_rendering.py
ppic/tests/test_request_repository.py
ppic-0.2.7.dist-info/LICENSE
ppic-0.2.7.dist-info/METADATA
ppic-0.2.7.dist-info/WHEEL
ppic-0.2.7.dist-info/entry_points.txt
ppic-0.2.7.dist-info/top_level.txt
ppic-0.2.7.dist-info/RECORD
