Metadata-Version: 2.1
Name: ppic
Version: 0.2.7
Summary: ppic is python package information collector.
Home-page: https://github.com/podhmo/ppic
Author: podhmo
Author-email: 
License: UNKNOWN
Platform: UNKNOWN
Classifier: Programming Language :: Python
Classifier: Programming Language :: Python :: Implementation :: CPython
Requires-Dist: pip
Requires-Dist: distlib
Provides-Extra: docs
Provides-Extra: testing
Requires-Dist: evilunit ; extra == 'testing'
